heroprotocol/__init__.py
heroprotocol/__main__.py
heroprotocol/build.py
heroprotocol/compat.py
heroprotocol/decoders.py
heroprotocol/hero_cli.py
heroprotocol/versions/__init__.py
heroprotocol/versions/protocol29406.py
heroprotocol/versions/protocol30414.py
heroprotocol/versions/protocol30509.py
heroprotocol/versions/protocol30829.py
heroprotocol/versions/protocol30948.py
heroprotocol/versions/protocol31090.py
heroprotocol/versions/protocol31360.py
heroprotocol/versions/protocol31566.py
heroprotocol/versions/protocol31726.py
heroprotocol/versions/protocol31948.py
heroprotocol/versions/protocol32120.py
heroprotocol/versions/protocol32253.py
heroprotocol/versions/protocol32455.py
heroprotocol/versions/protocol32524.py
heroprotocol/versions/protocol33182.py
heroprotocol/versions/protocol33353.py
heroprotocol/versions/protocol33684.py
heroprotocol/versions/protocol34053.py
heroprotocol/versions/protocol34190.py
heroprotocol/versions/protocol34659.py
heroprotocol/versions/protocol34846.py
heroprotocol/versions/protocol35360.py
heroprotocol/versions/protocol35529.py
heroprotocol/versions/protocol35634.py
heroprotocol/versions/protocol35702.py
heroprotocol/versions/protocol36144.py
heroprotocol/versions/protocol36280.py
heroprotocol/versions/protocol36359.py
heroprotocol/versions/protocol36536.py
heroprotocol/versions/protocol36693.py
heroprotocol/versions/protocol37069.py
heroprotocol/versions/protocol37117.py
heroprotocol/versions/protocol37274.py
heroprotocol/versions/protocol37351.py
heroprotocol/versions/protocol37569.py
heroprotocol/versions/protocol37795.py
heroprotocol/versions/protocol38236.py
heroprotocol/versions/protocol38500.py
heroprotocol/versions/protocol38593.py
heroprotocol/versions/protocol38793.py
heroprotocol/versions/protocol39015.py
heroprotocol/versions/protocol39153.py
heroprotocol/versions/protocol39271.py
heroprotocol/versions/protocol39445.py
heroprotocol/versions/protocol39595.py
heroprotocol/versions/protocol39709.py
heroprotocol-2.55.4.91756.dist-info/LICENSE
heroprotocol-2.55.4.91756.dist-info/METADATA
heroprotocol-2.55.4.91756.dist-info/WHEEL
heroprotocol-2.55.4.91756.dist-info/entry_points.txt
heroprotocol-2.55.4.91756.dist-info/top_level.txt
heroprotocol-2.55.4.91756.dist-info/RECORD
